{"14-06-2019": {"sagunwillbethere": {"info": "", "points": 0}, "raghav0296": {"info": "", "points": 0}}, "15-06-2019": {"sagunwillbethere": {"info": "meeting", "points": 10}, "raghav0296": {"info": "dl book, doubles", "points": 10}}, "06-07-2019": {"sagunwillbethere": {"info": "articles", "points": 20}, "raghav0296": {"info": "trackmyprogress", "points": 20}}, "07-07-2019": {"raghav0296": {"info": "update trackmyprogress", "points": 4}}, "08-07-2019": {"raghav0296": {"points": 10.0, "info": "Finished trackmyprogress"}}, "11-07-2019": {"raghav0296": {"info": "updated trackmyprogress; progressed visa question; ; update", "points": 18.0}}}